README.md
setup.py
tap_ebay/__init__.py
tap_ebay/client.py
tap_ebay/config.py
tap_ebay/state.py
tap_ebay.egg-info/PKG-INFO
tap_ebay.egg-info/SOURCES.txt
tap_ebay.egg-info/dependency_links.txt
tap_ebay.egg-info/entry_points.txt
tap_ebay.egg-info/requires.txt
tap_ebay.egg-info/top_level.txt
tap_ebay/schemas/orders.json
tap_ebay/streams/__init__.py
tap_ebay/streams/base.py
tap_ebay/streams/orders.py