Metadata-Version: 2.1
Name: tap-ebay
Version: 0.0.2
Summary: Singer.io tap for extracting data from the Ebay API
Home-page: http://fishtownanalytics.com
Author: Fishtown Analytics
License: UNKNOWN
Platform: UNKNOWN
Classifier: Programming Language :: Python :: 3 :: Only
Provides-Extra: dev
